PAsampling/__init__.py
PAsampling/native_functions/__init__.py
PAsampling/native_functions/da_fps.py
PAsampling/native_functions/fps.py
PAsampling/utils/__init__.py
PAsampling/utils/data_loader.py
PAsampling/utils/data_selection.py
PAsampling/wrappers/__init__.py
PAsampling/wrappers/dafps_sampler.py
PAsampling/wrappers/facility_location_sampler.py
PAsampling/wrappers/fps_plus_sampler.py
PAsampling/wrappers/fps_sampler.py
PAsampling/wrappers/kmedoids_sampler.py
PAsampling/wrappers/twin_sampler.py
PAsampling-0.0.1.dist-info/METADATA
PAsampling-0.0.1.dist-info/WHEEL
PAsampling-0.0.1.dist-info/top_level.txt
PAsampling-0.0.1.dist-info/RECORD
