Metadata-Version: 2.2
Name: PAsampling
Version: 0.0.1
Summary: A library for passive data sampling implementing existing and novel algorithms
Home-page: https://github.com/PaClimaco/PAsampling
Author: Paolo Climaco
Author-email: climaco@ins.uni-bonn.de
License: MIT
Classifier: Programming Language :: Python :: 3
Classifier: License :: OSI Approved :: MIT License
Classifier: Operating System :: OS Independent
Requires-Dist: numpy<2.0.0
Requires-Dist: ipywidgets
Requires-Dist: tqdm
Requires-Dist: scipy
Requires-Dist: scikit-learn
Requires-Dist: h5py
Requires-Dist: apricot-select==0.6.0
Requires-Dist: scikit-learn-extra==0.2.0
Requires-Dist: matplotlib
Requires-Dist: seaborn
Requires-Dist: pandas
Requires-Dist: twinning
Requires-Dist: requests
Dynamic: author
Dynamic: author-email
Dynamic: classifier
Dynamic: home-page
Dynamic: license
Dynamic: requires-dist
Dynamic: summary
